orderlyweb_api/__init__.py
orderlyweb_api/orderly_web_api.py
orderlyweb_api/orderly_web_response_error.py
orderlyweb_api/result_models.py
test/__init__.py
test/integration/__init__.py
test/integration/test_orderly_web_api.py
test/unit/__init__.py
test/unit/test_orderly_web_api.py
test/unit/test_orderly_web_response_error.py
test/unit/test_report_status_result.py
test/unit/test_version_details.py
orderlyweb_api-1.0.0.dist-info/LICENSE
orderlyweb_api-1.0.0.dist-info/METADATA
orderlyweb_api-1.0.0.dist-info/WHEEL
orderlyweb_api-1.0.0.dist-info/top_level.txt
orderlyweb_api-1.0.0.dist-info/RECORD
