Metadata-Version: 2.1
Name: orderlyweb-api
Version: 1.0.0
Summary: Python client for OrderlyWeb API
Home-page: https://github.com/vimc/orderlyweb-py
Author: Emma Russell
Author-email: e.russell@imperial.ac.uk
License: MIT
Platform: UNKNOWN
Classifier: Programming Language :: Python :: 3
Classifier: License :: OSI Approved :: MIT License
Classifier: Operating System :: OS Independent
License-File: LICENSE
Requires-Dist: requests
Requires-Dist: pytest
